downforeveryone/__init__.py
downforeveryone/cli.py
downforeveryone/constants.py
downforeveryone/isup.py
downforeveryone/useragents.json
downforeveryone/useragents.py
downforeveryone-1.0.7.dist-info/LICENSE
downforeveryone-1.0.7.dist-info/METADATA
downforeveryone-1.0.7.dist-info/WHEEL
downforeveryone-1.0.7.dist-info/entry_points.txt
downforeveryone-1.0.7.dist-info/RECORD
