Metadata-Version: 2.3
Name: downforeveryone
Version: 1.0.7
Summary: checks if a website is really down via isup.me
Author: Ryan Delaney
Author-email: ryan.patrick.delaney@protonmail.com
Requires-Python: >=3.8,<4.0
Classifier: Environment :: Console
Classifier: License :: OSI Approved :: Apache Software License
Classifier: Programming Language :: Python :: 3
Classifier: Programming Language :: Python :: 3.8
Classifier: Programming Language :: Python :: 3.9
Classifier: Programming Language :: Python :: 3.10
Classifier: Programming Language :: Python :: 3.11
Classifier: Programming Language :: Python :: 3.12
Classifier: Programming Language :: Python :: 3.13
Classifier: Programming Language :: Python :: 3 :: Only
Requires-Dist: requests (>=2.22,<3.0)
Project-URL: Homepage, https://pypi.org/project/downforeveryone
Project-URL: Repository, https://github.com/rpdelaney/downforeveryone
